pyhttptest/__init__.py
pyhttptest/cli.py
pyhttptest/constants.py
pyhttptest/core.py
pyhttptest/decorators.py
pyhttptest/exceptions.py
pyhttptest/http.py
pyhttptest/logger.py
pyhttptest/printer.py
pyhttptest/utils.py
pyhttptest/wrappers.py
pyhttptest/http_schemas/__init__.py
pyhttptest/http_schemas/base_schema.py
pyhttptest/http_schemas/delete_schema.py
pyhttptest/http_schemas/get_schema.py
pyhttptest/http_schemas/post_schema.py
pyhttptest/http_schemas/put_schema.py
pyhttptest-0.7.dist-info/LICENSE
pyhttptest-0.7.dist-info/METADATA
pyhttptest-0.7.dist-info/WHEEL
pyhttptest-0.7.dist-info/entry_points.txt
pyhttptest-0.7.dist-info/top_level.txt
pyhttptest-0.7.dist-info/RECORD
