Metadata-Version: 2.1
Name: pyhttptest
Version: 0.7
Summary: A command-line tool for HTTP tests over RESTful APIs
Home-page: https://github.com/slaily/pyhttptest
Author: Iliyan Slavov
Author-email: slavov.iliyan96@gmail.com
License: BSD 3-Clause License
Project-URL: Issues, https://github.com/slaily/pyhttptest/issues
Keywords: HTTP test RESTFul API JSON
Platform: UNKNOWN
Classifier: Development Status :: 5 - Production/Stable
Classifier: Environment :: Console
Classifier: Intended Audience :: Developers
Classifier: License :: OSI Approved :: BSD License
Classifier: Natural Language :: English
Classifier: Operating System :: OS Independent
Classifier: Programming Language :: Python :: 3
Classifier: Topic :: Software Development :: Testing
Requires-Python: >=3
Requires-Dist: click (==7.0)
Requires-Dist: ijson (==3.0.3)
Requires-Dist: jsonschema (==3.1.1)
Requires-Dist: requests (==2.22.0)
Requires-Dist: tabulate (==0.8.5)
